requirements.txt
setup.py
jsfiddle_readme_generator/__init__.py
jsfiddle_readme_generator/__main__.py
jsfiddle_readme_generator.egg-info/PKG-INFO
jsfiddle_readme_generator.egg-info/SOURCES.txt
jsfiddle_readme_generator.egg-info/dependency_links.txt
jsfiddle_readme_generator.egg-info/requires.txt
jsfiddle_readme_generator.egg-info/top_level.txt