Metadata-Version: 2.1
Name: jsfiddle-readme-generator
Version: 2020.7.1
Summary: generate jsfiddle README.md
Home-page: https://github.com/andrewp-as-is/jsfiddle-readme-generator.py
License: Unlicense
Keywords: jsfiddle
Platform: UNKNOWN
Classifier: License :: Public Domain
Classifier: Operating System :: OS Independent
Classifier: Programming Language :: Python :: 3
Classifier: Topic :: Documentation
